gpflux/__init__.py
gpflux/callbacks.py
gpflux/exceptions.py
gpflux/helpers.py
gpflux/losses.py
gpflux/math.py
gpflux/py.typed
gpflux/runtime_checks.py
gpflux/types.py
gpflux/version.py
gpflux/architectures/__init__.py
gpflux/architectures/constant_input_dim_deep_gp.py
gpflux/encoders/__init__.py
gpflux/encoders/directly_parameterized_encoder.py
gpflux/experiment_support/__init__.py
gpflux/experiment_support/ci_utils.py
gpflux/experiment_support/plotting.py
gpflux/experiment_support/tensorboard.py
gpflux/layers/__init__.py
gpflux/layers/bayesian_dense_layer.py
gpflux/layers/gp_layer.py
gpflux/layers/latent_variable_layer.py
gpflux/layers/likelihood_layer.py
gpflux/layers/trackable_layer.py
gpflux/layers/basis_functions/__init__.py
gpflux/layers/basis_functions/fourier_features/__init__.py
gpflux/layers/basis_functions/fourier_features/base.py
gpflux/layers/basis_functions/fourier_features/utils.py
gpflux/layers/basis_functions/fourier_features/quadrature/__init__.py
gpflux/layers/basis_functions/fourier_features/quadrature/gaussian.py
gpflux/layers/basis_functions/fourier_features/random/__init__.py
gpflux/layers/basis_functions/fourier_features/random/base.py
gpflux/layers/basis_functions/fourier_features/random/orthogonal.py
gpflux/models/__init__.py
gpflux/models/deep_gp.py
gpflux/optimization/__init__.py
gpflux/optimization/keras_natgrad.py
gpflux/sampling/__init__.py
gpflux/sampling/kernel_with_feature_decomposition.py
gpflux/sampling/sample.py
gpflux/sampling/utils.py
gpflux-0.4.4.dist-info/LICENSE
gpflux-0.4.4.dist-info/METADATA
gpflux-0.4.4.dist-info/WHEEL
gpflux-0.4.4.dist-info/top_level.txt
gpflux-0.4.4.dist-info/RECORD
