Metadata-Version: 2.1
Name: gpflux
Version: 0.4.4
Summary: GPflux: Deep GP library
Home-page: UNKNOWN
Author: Secondmind Labs
Author-email: gpflux@secondmind.ai
License: Apache License 2.0
Project-URL: Source on GitHub, https://github.com/secondmind-labs/GPflux
Project-URL: Documentation, https://secondmind-labs.github.io/GPflux/
Keywords: Deep-Gaussian-processes
Platform: UNKNOWN
Classifier: License :: OSI Approved :: Apache Software License
Classifier: Programming Language :: Python :: 3.7
Classifier: Programming Language :: Python :: 3.8
Classifier: Programming Language :: Python :: 3.9
Classifier: Programming Language :: Python :: 3.10
Classifier: Operating System :: OS Independent
Classifier: Topic :: Scientific/Engineering :: Artificial Intelligence
Requires-Dist: deprecated
Requires-Dist: gpflow >=2.9.2
Requires-Dist: numpy <2
Requires-Dist: scipy
Requires-Dist: tensorflow-probability <0.25,>=0.13.0
Requires-Dist: tensorflow <2.17,>=2.5.0 ; platform_system != "Darwin" or platform_machine != "arm64"
Requires-Dist: tensorflow-macos <2.17,>=2.5.0 ; platform_system == "Darwin" and platform_machine == "arm64"
